clouds2env.py
clouds2env-1.2.0.dist-info/LICENSE.rst
clouds2env-1.2.0.dist-info/METADATA
clouds2env-1.2.0.dist-info/WHEEL
clouds2env-1.2.0.dist-info/entry_points.txt
clouds2env-1.2.0.dist-info/top_level.txt
clouds2env-1.2.0.dist-info/RECORD
