Metadata-Version: 2.1
Name: clouds2env
Version: 1.2.0
Summary: A script to generate environment variables based on clouds.yaml details
Home-page: https://github.com/stephenfin/clouds2env
Author: Stephen Finucane
Author-email: stephen@that.guru
License: MIT
Keywords: openstack
Classifier: Development Status :: 5 - Production/Stable
Classifier: Environment :: OpenStack
Classifier: Intended Audience :: Information Technology
Classifier: Intended Audience :: System Administrators
Classifier: License :: OSI Approved :: Apache Software License
Classifier: Operating System :: POSIX :: Linux
Classifier: Programming Language :: Python
Classifier: Programming Language :: Python :: 3
Classifier: Programming Language :: Python :: 3.7
Classifier: Programming Language :: Python :: 3.8
Classifier: Programming Language :: Python :: 3.9
Classifier: Programming Language :: Python :: 3.10
Classifier: Programming Language :: Python :: 3 :: Only
License-File: LICENSE.rst
Requires-Dist: PyYAML
